{
  "attributes": [
    {
      "allow_nil?": false,
      "default": "fragment(\"gen_random_uuid()\")",
      "generated?": false,
      "precision": null,
      "primary_key?": true,
      "references": null,
      "scale": null,
      "size": null,
      "source": "id",
      "type": "uuid"
    },
    {
      "allow_nil?": false,
      "default": "nil",
      "generated?": false,
      "precision": null,
      "primary_key?": false,
      "references": null,
      "scale": null,
      "size": null,
      "source": "channel_name",
      "type": "text"
    },
    {
      "allow_nil?": false,
      "default": "nil",
      "generated?": false,
      "precision": null,
      "primary_key?": false,
      "references": null,
      "scale": null,
      "size": null,
      "source": "channel_slug",
      "type": "text"
    },
    {
      "allow_nil?": false,
      "default": "\"text\"",
      "generated?": false,
      "precision": null,
      "primary_key?": false,
      "references": null,
      "scale": null,
      "size": null,
      "source": "channel_type",
      "type": "text"
    },
    {
      "allow_nil?": true,
      "default": "nil",
      "generated?": false,
      "precision": null,
      "primary_key?": false,
      "references": null,
      "scale": null,
      "size": null,
      "source": "channel_category",
      "type": "text"
    },
    {
      "allow_nil?": false,
      "default": "\"active\"",
      "generated?": false,
      "precision": null,
      "primary_key?": false,
      "references": null,
      "scale": null,
      "size": null,
      "source": "status",
      "type": "text"
    },
    {
      "allow_nil?": false,
      "default": "\"public\"",
      "generated?": false,
      "precision": null,
      "primary_key?": false,
      "references": null,
      "scale": null,
      "size": null,
      "source": "visibility",
      "type": "text"
    },
    {
      "allow_nil?": true,
      "default": "nil",
      "generated?": false,
      "precision": null,
      "primary_key?": false,
      "references": null,
      "scale": null,
      "size": null,
      "source": "topic",
      "type": "text"
    },
    {
      "allow_nil?": false,
      "default": "nil",
      "generated?": false,
      "precision": null,
      "primary_key?": false,
      "references": null,
      "scale": null,
      "size": null,
      "source": "channel_config",
      "type": "map"
    },
    {
      "allow_nil?": false,
      "default": "nil",
      "generated?": false,
      "precision": null,
      "primary_key?": false,
      "references": null,
      "scale": null,
      "size": null,
      "source": "voice_config",
      "type": "map"
    },
    {
      "allow_nil?": false,
      "default": "%{}",
      "generated?": false,
      "precision": null,
      "primary_key?": false,
      "references": null,
      "scale": null,
      "size": null,
      "source": "permissions_override",
      "type": "map"
    },
    {
      "allow_nil?": false,
      "default": "0",
      "generated?": false,
      "precision": null,
      "primary_key?": false,
      "references": null,
      "scale": null,
      "size": null,
      "source": "message_count",
      "type": "bigint"
    },
    {
      "allow_nil?": false,
      "default": "0",
      "generated?": false,
      "precision": null,
      "primary_key?": false,
      "references": null,
      "scale": null,
      "size": null,
      "source": "active_participants",
      "type": "bigint"
    },
    {
      "allow_nil?": true,
      "default": "nil",
      "generated?": false,
      "precision": null,
      "primary_key?": false,
      "references": null,
      "scale": null,
      "size": null,
      "source": "last_message_at",
      "type": "utc_datetime"
    },
    {
      "allow_nil?": false,
      "default": "nil",
      "generated?": false,
      "precision": null,
      "primary_key?": false,
      "references": null,
      "scale": null,
      "size": null,
      "source": "created_by",
      "type": "uuid"
    },
    {
      "allow_nil?": false,
      "default": "[]",
      "generated?": false,
      "precision": null,
      "primary_key?": false,
      "references": null,
      "scale": null,
      "size": null,
      "source": "pinned_message_ids",
      "type": [
        "array",
        "uuid"
      ]
    },
    {
      "allow_nil?": false,
      "default": "nil",
      "generated?": false,
      "precision": null,
      "primary_key?": false,
      "references": null,
      "scale": null,
      "size": null,
      "source": "channel_integrations",
      "type": "map"
    },
    {
      "allow_nil?": false,
      "default": "nil",
      "generated?": false,
      "precision": null,
      "primary_key?": false,
      "references": null,
      "scale": null,
      "size": null,
      "source": "moderation_config",
      "type": "map"
    },
    {
      "allow_nil?": false,
      "default": "nil",
      "generated?": false,
      "precision": null,
      "primary_key?": false,
      "references": null,
      "scale": null,
      "size": null,
      "source": "channel_metrics",
      "type": "map"
    },
    {
      "allow_nil?": false,
      "default": "0",
      "generated?": false,
      "precision": null,
      "primary_key?": false,
      "references": null,
      "scale": null,
      "size": null,
      "source": "position",
      "type": "bigint"
    },
    {
      "allow_nil?": false,
      "default": "[]",
      "generated?": false,
      "precision": null,
      "primary_key?": false,
      "references": null,
      "scale": null,
      "size": null,
      "source": "tags",
      "type": [
        "array",
        "text"
      ]
    },
    {
      "allow_nil?": false,
      "default": "%{}",
      "generated?": false,
      "precision": null,
      "primary_key?": false,
      "references": null,
      "scale": null,
      "size": null,
      "source": "metadata",
      "type": "map"
    },
    {
      "allow_nil?": false,
      "default": "fragment(\"(now() AT TIME ZONE 'utc')\")",
      "generated?": false,
      "precision": null,
      "primary_key?": false,
      "references": null,
      "scale": null,
      "size": null,
      "source": "inserted_at",
      "type": "utc_datetime_usec"
    },
    {
      "allow_nil?": false,
      "default": "fragment(\"(now() AT TIME ZONE 'utc')\")",
      "generated?": false,
      "precision": null,
      "primary_key?": false,
      "references": null,
      "scale": null,
      "size": null,
      "source": "updated_at",
      "type": "utc_datetime_usec"
    },
    {
      "allow_nil?": true,
      "default": "nil",
      "generated?": false,
      "precision": null,
      "primary_key?": false,
      "references": {
        "deferrable": false,
        "destination_attribute": "id",
        "destination_attribute_default": null,
        "destination_attribute_generated": null,
        "index?": false,
        "match_type": null,
        "match_with": null,
        "multitenancy": {
          "attribute": null,
          "global": null,
          "strategy": null
        },
        "name": "thunderblock_channels_community_id_fkey",
        "on_delete": "delete",
        "on_update": "update",
        "primary_key?": true,
        "schema": "public",
        "table": "thunderblock_communities"
      },
      "scale": null,
      "size": null,
      "source": "community_id",
      "type": "uuid"
    }
  ],
  "base_filter": null,
  "check_constraints": [],
  "custom_indexes": [
    {
      "all_tenants?": false,
      "concurrently": false,
      "error_fields": [
        "channel_slug",
        "community_id"
      ],
      "fields": [
        {
          "type": "atom",
          "value": "channel_slug"
        },
        {
          "type": "atom",
          "value": "community_id"
        }
      ],
      "include": null,
      "message": null,
      "name": "channels_slug_community_idx",
      "nulls_distinct": true,
      "prefix": null,
      "table": null,
      "unique": true,
      "using": null,
      "where": null
    },
    {
      "all_tenants?": false,
      "concurrently": false,
      "error_fields": [
        "community_id",
        "channel_type"
      ],
      "fields": [
        {
          "type": "atom",
          "value": "community_id"
        },
        {
          "type": "atom",
          "value": "channel_type"
        }
      ],
      "include": null,
      "message": null,
      "name": "channels_community_type_idx",
      "nulls_distinct": true,
      "prefix": null,
      "table": null,
      "unique": false,
      "using": null,
      "where": null
    },
    {
      "all_tenants?": false,
      "concurrently": false,
      "error_fields": [
        "community_id",
        "position"
      ],
      "fields": [
        {
          "type": "atom",
          "value": "community_id"
        },
        {
          "type": "atom",
          "value": "position"
        }
      ],
      "include": null,
      "message": null,
      "name": "channels_community_position_idx",
      "nulls_distinct": true,
      "prefix": null,
      "table": null,
      "unique": false,
      "using": null,
      "where": null
    },
    {
      "all_tenants?": false,
      "concurrently": false,
      "error_fields": [
        "channel_type",
        "status"
      ],
      "fields": [
        {
          "type": "atom",
          "value": "channel_type"
        },
        {
          "type": "atom",
          "value": "status"
        }
      ],
      "include": null,
      "message": null,
      "name": "channels_type_status_idx",
      "nulls_distinct": true,
      "prefix": null,
      "table": null,
      "unique": false,
      "using": null,
      "where": null
    },
    {
      "all_tenants?": false,
      "concurrently": false,
      "error_fields": [
        "status",
        "last_message_at"
      ],
      "fields": [
        {
          "type": "atom",
          "value": "status"
        },
        {
          "type": "atom",
          "value": "last_message_at"
        }
      ],
      "include": null,
      "message": null,
      "name": "channels_activity_idx",
      "nulls_distinct": true,
      "prefix": null,
      "table": null,
      "unique": false,
      "using": null,
      "where": null
    },
    {
      "all_tenants?": false,
      "concurrently": false,
      "error_fields": [
        "visibility",
        "status"
      ],
      "fields": [
        {
          "type": "atom",
          "value": "visibility"
        },
        {
          "type": "atom",
          "value": "status"
        }
      ],
      "include": null,
      "message": null,
      "name": "channels_visibility_idx",
      "nulls_distinct": true,
      "prefix": null,
      "table": null,
      "unique": false,
      "using": null,
      "where": null
    },
    {
      "all_tenants?": false,
      "concurrently": false,
      "error_fields": [],
      "fields": [
        {
          "type": "string",
          "value": "USING GIN (pinned_message_ids)"
        }
      ],
      "include": null,
      "message": null,
      "name": "channels_pinned_messages_idx",
      "nulls_distinct": true,
      "prefix": null,
      "table": null,
      "unique": false,
      "using": null,
      "where": null
    },
    {
      "all_tenants?": false,
      "concurrently": false,
      "error_fields": [],
      "fields": [
        {
          "type": "string",
          "value": "USING GIN (tags)"
        }
      ],
      "include": null,
      "message": null,
      "name": "channels_tags_idx",
      "nulls_distinct": true,
      "prefix": null,
      "table": null,
      "unique": false,
      "using": null,
      "where": null
    },
    {
      "all_tenants?": false,
      "concurrently": false,
      "error_fields": [],
      "fields": [
        {
          "type": "string",
          "value": "USING GIN (channel_metrics)"
        }
      ],
      "include": null,
      "message": null,
      "name": "channels_metrics_idx",
      "nulls_distinct": true,
      "prefix": null,
      "table": null,
      "unique": false,
      "using": null,
      "where": null
    }
  ],
  "custom_statements": [],
  "has_create_action": true,
  "hash": "A230EC7B8965E28C1057E98E14CBA267D0772438A616FDE1576414ACAD9B56EC",
  "identities": [
    {
      "all_tenants?": false,
      "base_filter": null,
      "index_name": "thunderblock_channels_unique_channel_in_community_index",
      "keys": [
        {
          "type": "atom",
          "value": "channel_slug"
        },
        {
          "type": "atom",
          "value": "community_id"
        }
      ],
      "name": "unique_channel_in_community",
      "nils_distinct?": true,
      "where": null
    }
  ],
  "multitenancy": {
    "attribute": null,
    "global": null,
    "strategy": null
  },
  "repo": "Elixir.Thunderline.Repo",
  "schema": null,
  "table": "thunderblock_channels"
}